setup.cfg
setup.py
DjangoRestless.egg-info/PKG-INFO
DjangoRestless.egg-info/SOURCES.txt
DjangoRestless.egg-info/dependency_links.txt
DjangoRestless.egg-info/requires.txt
DjangoRestless.egg-info/top_level.txt
restless/__init__.py
restless/auth.py
restless/http.py
restless/models.py
restless/modelviews.py
restless/views.py