Metadata-Version: 1.1
Name: DjangoRestless
Version: 0.0.6
Summary: A RESTful framework for Django
Home-page: github.com/dobarkod/django-restless
Author: Senko Rasic
Author-email: senko.rasic@goodcode.io
License: MIT
Platform: UNKNOWN
Classifier: Development Status :: 4 - Beta
Classifier: Environment :: Web Environment
Classifier: Framework :: Django
Classifier: Intended Audience :: Developers
Classifier: License :: OSI Approved :: MIT License
Classifier: Programming Language :: Python
Classifier: Programming Language :: Python :: 3
Classifier: Topic :: Software Development :: Libraries :: Python Modules
